smart_git_commit/__init__.py
smart_git_commit/smart_git_commit.py
smart_git_commit-0.2.3.dist-info/licenses/LICENSE
smart_git_commit-0.2.3.dist-info/METADATA
smart_git_commit-0.2.3.dist-info/WHEEL
smart_git_commit-0.2.3.dist-info/entry_points.txt
smart_git_commit-0.2.3.dist-info/top_level.txt
smart_git_commit-0.2.3.dist-info/RECORD
