Metadata-Version: 2.4
Name: smart-git-commit
Version: 0.2.3
Summary: AI-powered Git commit workflow tool
Home-page: https://github.com/CripterHack/smart-git-commit
Author: Edgar Zorrilla
Author-email: Edgar Zorrilla <edgar@izignamx.com>
License: MIT
Project-URL: Homepage, https://github.com/CripterHack/smart-git-commit
Project-URL: Issues, https://github.com/CripterHack/smart-git-commit/issues
Classifier: Development Status :: 4 - Beta
Classifier: Environment :: Console
Classifier: Intended Audience :: Developers
Classifier: License :: OSI Approved :: MIT License
Classifier: Operating System :: OS Independent
Classifier: Programming Language :: Python :: 3
Classifier: Programming Language :: Python :: 3.7
Classifier: Programming Language :: Python :: 3.8
Classifier: Programming Language :: Python :: 3.9
Classifier: Programming Language :: Python :: 3.10
Classifier: Topic :: Software Development :: Version Control :: Git
Requires-Python: >=3.7
License-File: LICENSE
Requires-Dist: psutil>=5.9.0
Provides-Extra: dev
Requires-Dist: pytest>=7.0.0; extra == "dev"
Requires-Dist: coverage>=6.0.0; extra == "dev"
Requires-Dist: black>=22.0.0; extra == "dev"
Requires-Dist: isort>=5.0.0; extra == "dev"
Requires-Dist: ruff>=0.0.85; extra == "dev"
Dynamic: author
Dynamic: home-page
Dynamic: license-file
Dynamic: requires-python
